LICENSE
README.md
setup.py
pychatsonic/_init_.py
pychatsonic/chat.py
pychatsonic.egg-info/PKG-INFO
pychatsonic.egg-info/SOURCES.txt
pychatsonic.egg-info/dependency_links.txt
pychatsonic.egg-info/not-zip-safe
pychatsonic.egg-info/top_level.txt