Metadata-Version: 2.1
Name: pychatsonic
Version: 0.1
Summary: Python adapter for chatsonic api
Author-email: weirdoo145@gmail.com
Requires: requests
License-File: LICENSE
